{
    "domain": "medicine",
    "concept": "brain structure",
    "definition": "structural or functional unit of the brain",
    "selection_criteria": [
        "it is a structural or functional unit of the brain"
    ],
    "ontology": "MeSH",
    "ontology_id": "D001921",
    "referents": {
        "Limbic System": {
            "Amygdala": {
                "Basolateral Nuclear Complex": {},
                "Central Amygdaloid Nucleus": {},
                "Corticomedial Nuclear Complex": {
                    "Periamygdaloid Cortex": {}
                }
            },
            "Hypothalamus": {
                "Middle Hypothalamus": {
                    "Arcuate Nucleus of Hypothalamus": {},
                    "Dorsomedial Hypothalamic Nucleus": {},
                    "Hypothalamo-Hypophyseal System": {
                        "Median Eminence": {},
                        "Pituitary Gland": {
                            "Anterior Pituitary Gland": {
                                "Corticotrophs": {},
                                "Gonadotrophs": {},
                                "Lactotrophs": {},
                                "Somatotrophs": {},
                                "Thyrotrophs": {}
                            },
                            "Posterior Pituitary Gland": {},
                            "Intermediate Pituitary Gland": {
                                "Melanotrophs": {}
                            }
                        },
                        "Hypothalamic-Pituitary-Gonadal Axis": {}
                    },
                    "Tuber Cinereum": {},
                    "Ventromedial Hypothalamic Nucleus": {}
                },
                "Anterior Hypothalamus": {
                    "Anterior Hypothalamic Nucleus": {},
                    "Paraventricular Hypothalamic Nucleus": {},
                    "Preoptic Area": {},
                    "Suprachiasmatic Nucleus": {
                        "Suprachiasmatic Nucleus Neurons": {}
                    },
                    "Supraoptic Nucleus": {},
                    "Organum Vasculosum": {}
                },
                "Lateral Hypothalamic Area": {},
                "Posterior Hypothalamus": {
                    "Mammillary Bodies": {}
                }
            },
            "Limbic Lobe": {
                "Gyrus Cinguli": {},
                "Parahippocampal Gyrus": {
                    "Entorhinal Cortex": {},
                    "Periamygdaloid Cortex": {}
                }
            },
            "Hippocampus": {
                "Dentate Gyrus": {
                    "Hippocampal Mossy Fibers": {}
                },
                "Brain Fornix": {},
                "Hippocampal CA1 Region": {},
                "Hippocampal CA2 Region": {},
                "Hippocampal CA3 Region": {},
                "Schaffer Collaterals": {}
            },
            "Olfactory Pathways": {},
            "Epithalamus": {
                "Pineal Gland": {},
                "Habenula": {}
            },
            "Septum of Brain": {
                "Septal Nuclei": {},
                "Septum Pellucidum": {}
            },
            "Substantia Innominata": {},
            "Perforant Pathway": {}
        },
        "Prosencephalon": {
            "Telencephalon": {
                "Cerebrum": {
                    "Basal Ganglia": {
                        "Amygdala": {
                            "Basolateral Nuclear Complex": {},
                            "Central Amygdaloid Nucleus": {},
                            "Corticomedial Nuclear Complex": {
                                "Periamygdaloid Cortex": {}
                            }
                        },
                        "Corpus Striatum": {
                            "Neostriatum": {
                                "Caudate Nucleus": {},
                                "Putamen": {},
                                "High Vocal Center": {}
                            },
                            "Globus Pallidus": {},
                            "Ventral Striatum": {
                                "Nucleus Accumbens": {},
                                "Olfactory Tubercle": {
                                    "Islands of Calleja": {}
                                }
                            }
                        },
                        "Substantia Innominata": {
                            "Basal Nucleus of Meynert": {}
                        },
                        "Claustrum": {}
                    },
                    "Cerebral Cortex": {
                        "Sensorimotor Cortex": {
                            "Auditory Cortex": {},
                            "Motor Cortex": {},
                            "Somatosensory Cortex": {},
                            "Visual Cortex": {
                                "Primary Visual Cortex": {}
                            },
                            "Olfactory Cortex": {
                                "Entorhinal Cortex": {},
                                "Olfactory Tubercle": {
                                    "Islands of Calleja": {}
                                },
                                "Basal Forebrain": {
                                    "Organum Vasculosum": {}
                                },
                                "Piriform Cortex": {}
                            }
                        },
                        "Temporal Lobe": {
                            "Auditory Cortex": {},
                            "Wernicke Area": {},
                            "Perirhinal Cortex": {},
                            "Uncinate Fasciculus": {}
                        },
                        "Frontal Lobe": {
                            "Motor Cortex": {},
                            "Prefrontal Cortex": {
                                "Broca Area": {},
                                "Dorsolateral Prefrontal Cortex": {}
                            },
                            "Uncinate Fasciculus": {}
                        },
                        "Limbic Lobe": {
                            "Gyrus Cinguli": {},
                            "Parahippocampal Gyrus": {
                                "Entorhinal Cortex": {},
                                "Periamygdaloid Cortex": {}
                            }
                        },
                        "Hippocampus": {
                            "Dentate Gyrus": {
                                "Hippocampal Mossy Fibers": {}
                            },
                            "Brain Fornix": {},
                            "Hippocampal CA1 Region": {},
                            "Hippocampal CA2 Region": {},
                            "Hippocampal CA3 Region": {},
                            "Schaffer Collaterals": {}
                        },
                        "Occipital Lobe": {
                            "Visual Cortex": {
                                "Primary Visual Cortex": {}
                            }
                        },
                        "Parietal Lobe": {
                            "Somatosensory Cortex": {},
                            "Wernicke Area": {}
                        },
                        "Neocortex": {
                            "Ganglionic Eminence": {}
                        },
                        "Insular Cortex": {}
                    },
                    "Olfactory Cortex": {
                        "Entorhinal Cortex": {},
                        "Olfactory Tubercle": {
                            "Islands of Calleja": {}
                        },
                        "Basal Forebrain": {},
                        "Piriform Cortex": {}
                    }
                },
                "Telencephalic Commissures": {
                    "Corpus Callosum": {},
                    "Brain Anterior Commissure": {}
                },
                "Olfactory Bulb": {},
                "Septum of Brain": {
                    "Septal Nuclei": {},
                    "Septum Pellucidum": {}
                },
                "Diagonal Band of Broca": {},
                "Internal Capsule": {},
                "External Capsule": {}
            },
            "Diencephalon": {
                "Hypothalamus": {
                    "Middle Hypothalamus": {
                        "Arcuate Nucleus of Hypothalamus": {},
                        "Dorsomedial Hypothalamic Nucleus": {},
                        "Hypothalamo-Hypophyseal System": {
                            "Median Eminence": {},
                            "Pituitary Gland": {
                                "Anterior Pituitary Gland": {
                                    "Corticotrophs": {},
                                    "Gonadotrophs": {},
                                    "Lactotrophs": {},
                                    "Somatotrophs": {},
                                    "Thyrotrophs": {}
                                },
                                "Posterior Pituitary Gland": {},
                                "Intermediate Pituitary Gland": {
                                    "Melanotrophs": {}
                                }
                            },
                            "Hypothalamic-Pituitary-Gonadal Axis": {}
                        },
                        "Tuber Cinereum": {},
                        "Ventromedial Hypothalamic Nucleus": {}
                    },
                    "Anterior Hypothalamus": {
                        "Anterior Hypothalamic Nucleus": {},
                        "Paraventricular Hypothalamic Nucleus": {},
                        "Preoptic Area": {},
                        "Suprachiasmatic Nucleus": {
                            "Suprachiasmatic Nucleus Neurons": {}
                        },
                        "Supraoptic Nucleus": {},
                        "Organum Vasculosum": {}
                    },
                    "Lateral Hypothalamic Area": {},
                    "Posterior Hypothalamus": {
                        "Mammillary Bodies": {}
                    }
                },
                "Thalamus": {
                    "Thalamic Nuclei": {
                        "Geniculate Bodies": {},
                        "Anterior Thalamic Nuclei": {},
                        "Midline Thalamic Nuclei": {},
                        "Mediodorsal Thalamic Nucleus": {},
                        "Intralaminar Thalamic Nuclei": {},
                        "Lateral Thalamic Nuclei": {
                            "Pulvinar": {}
                        },
                        "Ventral Thalamic Nuclei": {},
                        "Posterior Thalamic Nuclei": {}
                    }
                },
                "Optic Chiasm": {},
                "Epithalamus": {
                    "Pineal Gland": {},
                    "Habenula": {}
                },
                "Subthalamus": {
                    "Entopeduncular Nucleus": {},
                    "Subthalamic Nucleus": {},
                    "Zona Incerta": {}
                },
                "Optic Tract": {}
            }
        },
        "Blood-Brain Barrier": {},
        "Brain Stem": {
            "Rhombencephalon": {
                "Metencephalon": {
                    "Cerebellum": {
                        "Cerebellar Cortex": {
                            "Purkinje Cells": {},
                            "Cerebellar Vermis": {},
                            "Cerebellar Golgi Cells": {}
                        },
                        "Cerebellar Nuclei": {},
                        "Cerebellopontine Angle": {}
                    },
                    "Pons": {
                        "Vestibular Nuclei": {
                            "Lateral Vestibular Nucleus": {}
                        },
                        "Pontine Tegmentum": {
                            "Locus Coeruleus": {},
                            "Raphe Nuclei": {
                                "Nucleus Raphe Magnus": {}
                            },
                            "Spinal Trigeminal Nucleus": {},
                            "Parabrachial Nucleus": {},
                            "Abducens Nucleus": {},
                            "Facial Nucleus": {},
                            "Superior Olivary Complex": {},
                            "Trapezoid Body": {},
                            "Trigeminal Motor Nucleus": {}
                        },
                        "Cochlear Nucleus": {},
                        "Barrington's Nucleus": {},
                        "Kolliker-Fuse Nucleus": {},
                        "Middle Cerebellar Peduncle": {}
                    }
                },
                "Myelencephalon": {
                    "Medulla Oblongata": {
                        "Raphe Nuclei": {
                            "Nucleus Raphe Pallidus": {},
                            "Nucleus Raphe Obscurus": {}
                        },
                        "Spinal Trigeminal Nucleus": {
                            "Trigeminal Caudal Nucleus": {}
                        },
                        "Solitary Nucleus": {},
                        "Area Postrema": {},
                        "Inferior Olivary Complex": {}
                    },
                    "Olivary Nucleus": {
                        "Superior Olivary Complex": {},
                        "Inferior Olivary Complex": {}
                    }
                },
                "Tectospinal Fibers": {}
            },
            "Mesencephalon": {
                "Cerebral Peduncle": {
                    "Tegmentum Mesencephali": {
                        "Cerebral Aqueduct": {},
                        "Periaqueductal Gray": {},
                        "Raphe Nuclei": {
                            "Dorsal Raphe Nucleus": {},
                            "Midbrain Raphe Nuclei": {},
                            "Interpeduncular Nucleus": {}
                        },
                        "Red Nucleus": {},
                        "Ventral Tegmental Area": {},
                        "Midbrain Reticular Formation": {
                            "Pedunculopontine Tegmental Nucleus": {}
                        },
                        "Oculomotor Nuclear Complex": {
                            "Edinger-Westphal Nucleus": {}
                        }
                    },
                    "Substantia Nigra": {
                        "Pars Reticulata": {},
                        "Pars Compacta": {}
                    },
                    "Cerebral Crus": {}
                },
                "Tectum Mesencephali": {
                    "Inferior Colliculi": {},
                    "Subcommissural Organ": {},
                    "Superior Colliculi": {},
                    "Posterior Cerebellar Commissure": {},
                    "Pretectal Region": {}
                },
                "Locus Coeruleus": {}
            },
            "Reticular Formation": {
                "Respiratory Center": {},
                "Midbrain Reticular Formation": {
                    "Pedunculopontine Tegmental Nucleus": {}
                }
            },
            "Trigeminal Nuclei": {
                "Spinal Trigeminal Nucleus": {
                    "Trigeminal Caudal Nucleus": {}
                },
                "Trigeminal Motor Nucleus": {}
            }
        },
        "Cerebral Ventricles": {
            "Cerebral Aqueduct": {},
            "Choroid Plexus": {},
            "Ependyma": {},
            "Septum Pellucidum": {},
            "Third Ventricle": {},
            "Fourth Ventricle": {},
            "Lateral Ventricles": {}
        },
        "White Matter": {},
        "Gray Matter": {},
        "Glymphatic System": {}
    }
}