{
    "domain": "biology",
    "concept": "stromal cell",
    "definition": "Connective tissue cells of an organ found in the loose connective tissue.",
    "selection_criteria": [
        "it is a connective tissue cell",
        "it is found in the loose connective tissue"
    ],
    "ontology": "MeSH",
    "ontology_id": "D017154",
    "referents": {
        "Mesenchymal Stem Cells": {
            "Stromal Vascular Fraction": {}
        },
        "Telocytes": {
            "Telopodes": {}
        }
    }
}